LICENSE
MANIFEST.in
setup.py
fasttld/FastTLDExtract.py
fasttld/__init__.py
fasttld/psl.py
fasttld/public_suffix_list.dat
fasttld.egg-info/PKG-INFO
fasttld.egg-info/SOURCES.txt
fasttld.egg-info/dependency_links.txt
fasttld.egg-info/not-zip-safe
fasttld.egg-info/requires.txt
fasttld.egg-info/top_level.txt
tests/__init__.py
tests/maintest.py
tests/performance.py
tests/test.py