Metadata-Version: 1.1
Name: fasttld
Version: 0.2.1
Summary: Python high performance TLD extract module based on a compressed trie with builtin python dict.
Home-page: https://github.com/jophy/fasttld
Author: Jophy
Author-email: jophy.tsui@gmail.com
License: GPL
Platform: UNKNOWN
Classifier: Development Status :: 5 - Production/Stable
Classifier: Topic :: Utilities
Classifier: License :: OSI Approved :: MIT License
Classifier: Programming Language :: Python :: 2
Classifier: Programming Language :: Python :: 2.6
Classifier: Programming Language :: Python :: 2.7
Classifier: Programming Language :: Python :: 3
Classifier: Programming Language :: Python :: 3.3
Classifier: Programming Language :: Python :: 3.4
Classifier: Programming Language :: Python :: 3.5
Classifier: Programming Language :: Python :: 3.6
